{
  "News": [
    {
      "ImageLink": "img/news/new1.jpg",
      "Name": "KFC BATTLE",
      "Date": "15 ИЮНЯ",
      "Description": "ПОБЕДА НАША🔥<br><br>Суперфинал в Москве.",
      "PostLink": "https://vk.com/forsage_dance_school?w=wall-120234843_932"
    },
    {
      "ImageLink": "img/news/new2.jpg",
      "Name": "ДЕТИ В КАЗАНИ",
      "Date": "4 ИЮЛЯ",
      "Description": "SUMMER GROOVE CAMP<br><br>Пока летом все отдыхают, мы прокачиваемся",
      "PostLink": "https://vk.com/forsage_dance_school?w=wall-120234843_960"
    },
    {
      "ImageLink": "img/news/new3.jpg",
      "Name": "URAL DANCE CAMP",
      "Date": "23 АВГУСТА",
      "Description": "ТАНЦЕВАЛЬНЫЙ ЛАГЕРЬ В САМОМ СЕРДЦЕ УРАЛА<br><br>Получи 3 дня БЕСПЛАТНО!",
      "PostLink": "https://vk.com/ural_dance_camp?w=wall-170177924_54"
    }
  ]
}
